{
  "start_date": "1971-01-25",
  "end_date": "1971-01-29",
  "direction": "bullish",
  "prices": {
    "1971-01-25 00:00:00": {
      "('Open', 'JNJ')": 1.3177080154418945,
      "('High', 'JNJ')": 1.3203129768371582,
      "('Low', 'JNJ')": 1.3020830154418945,
      "('Close', 'JNJ')": 1.3072919845581055
    },
    "1971-01-26 00:00:00": {
      "('Open', 'JNJ')": 1.328125,
      "('High', 'JNJ')": 1.3411459922790527,
      "('Low', 'JNJ')": 1.328125,
      "('Close', 'JNJ')": 1.3411459922790527
    },
    "1971-01-27 00:00:00": {
      "('Open', 'JNJ')": 1.3411459922790527,
      "('High', 'JNJ')": 1.34375,
      "('Low', 'JNJ')": 1.3229169845581055,
      "('Close', 'JNJ')": 1.3229169845581055
    },
    "1971-01-28 00:00:00": {
      "('Open', 'JNJ')": 1.328125,
      "('High', 'JNJ')": 1.34375,
      "('Low', 'JNJ')": 1.328125,
      "('Close', 'JNJ')": 1.328125
    },
    "1971-01-29 00:00:00": {
      "('Open', 'JNJ')": 1.328125,
      "('High', 'JNJ')": 1.34375,
      "('Low', 'JNJ')": 1.3229169845581055,
      "('Close', 'JNJ')": 1.34375
    }
  },
  "duration": 5
}