{
  "start_date": "1986-03-05",
  "end_date": "1986-03-11",
  "direction": "bullish",
  "prices": {
    "1986-03-05 00:00:00": {
      "('Open', 'TXN')": 2.5104169845581055,
      "('High', 'TXN')": 2.5286459922790527,
      "('Low', 'TXN')": 2.4791669845581055,
      "('Close', 'TXN')": 2.5286459922790527
    },
    "1986-03-06 00:00:00": {
      "('Open', 'TXN')": 2.5520830154418945,
      "('High', 'TXN')": 2.5677080154418945,
      "('Low', 'TXN')": 2.5416669845581055,
      "('Close', 'TXN')": 2.5572919845581055
    },
    "1986-03-07 00:00:00": {
      "('Open', 'TXN')": 2.546875,
      "('High', 'TXN')": 2.5989580154418945,
      "('Low', 'TXN')": 2.5364580154418945,
      "('Close', 'TXN')": 2.5364580154418945
    },
    "1986-03-10 00:00:00": {
      "('Open', 'TXN')": 2.5416669845581055,
      "('High', 'TXN')": 2.5520830154418945,
      "('Low', 'TXN')": 2.523437976837158,
      "('Close', 'TXN')": 2.5494790077209473
    },
    "1986-03-11 00:00:00": {
      "('Open', 'TXN')": 2.570312976837158,
      "('High', 'TXN')": 2.6458330154418945,
      "('Low', 'TXN')": 2.546875,
      "('Close', 'TXN')": 2.6302080154418945
    }
  },
  "duration": 7
}